<?xml version = '1.0' encoding = 'UTF-8'?>
<TableProxyOraclev11g class="oracle.dbtools.crest.model.design.storage.oracle.v11g.TableProxyOraclev11g" name="CUSTOMER" directorySegmentName="seg_0" id="C794E5B7-7BF7-99DF-C51A-AC4E722D7374">
<createdBy>morne</createdBy>
<createdTime>2019-05-10 06:38:59 UTC</createdTime>
<ownerDesignName>testDB</ownerDesignName>
<schemaObject>06F01A99-A511-6603-9D38-8C774CE4E093</schemaObject>
<logging>YES</logging>
<partitionedRowMovement>DISABLE</partitionedRowMovement>
<segment>B28AE6C7-A112-C288-51F0-C65519F73119</segment>
<tableSpace>577F16CB-4515-0AC8-9A34-547917F569D0</tableSpace>
<temporaryChanged>false</temporaryChanged>
<accessDriverType>oracle_loader</accessDriverType>
<rejectLimit></rejectLimit>
<columnProxies itemClass="oracle.dbtools.crest.model.design.storage.oracle.v12c.ColumnProxyOraclev12c">
<ColumnProxy name="PERSONID" id="3AAC10A2-CDD5-06DA-72F1-B4FDF504101A">
<createdBy>morne</createdBy>
<createdTime>2019-05-10 06:38:59 UTC</createdTime>
<ownerDesignName>testDB</ownerDesignName>
</ColumnProxy>
<ColumnProxy name="SUBSCRIPTION_TYPE" id="DCA2B9AC-7154-9F0F-346F-7DD743368DFA">
<createdBy>morne</createdBy>
<createdTime>2019-05-10 06:38:59 UTC</createdTime>
<ownerDesignName>testDB</ownerDesignName>
</ColumnProxy>
<ColumnProxy name="PERSONTYPE" id="F5F81D02-6D9D-6D86-7FD2-CF4F8678715C">
<createdBy>morne</createdBy>
<createdTime>2019-05-10 06:38:59 UTC</createdTime>
<ownerDesignName>testDB</ownerDesignName>
<defaultValue>&apos;C&apos;</defaultValue>
</ColumnProxy>
</columnProxies>
<indexProxies>
<IndexProxy class="oracle.dbtools.crest.model.design.storage.oracle.v10g.IndexProxyOraclev10g" name="CUSTOMER_PK" id="A1F5F6C1-4CE6-6F02-6B3D-D043EFBB0457">
<createdBy>morne</createdBy>
<createdTime>2019-05-10 06:38:59 UTC</createdTime>
<ownerDesignName>testDB</ownerDesignName>
<schemaObject>06F01A99-A511-6603-9D38-8C774CE4E093</schemaObject>
<segment>9F6B1C94-F925-41C6-409C-5430207B896B</segment>
<tableSpace>577F16CB-4515-0AC8-9A34-547917F569D0</tableSpace>
</IndexProxy>
</indexProxies>
<foreignKeys>
<ForeignKey class="oracle.dbtools.crest.model.design.storage.oracle.v10g.FKProxyOraclev10g" name="CUSTOMER_FK" id="F06B408A-0760-9C22-DD45-54AA16106C4B">
<createdBy>morne</createdBy>
<createdTime>2019-05-10 06:39:00 UTC</createdTime>
<ownerDesignName>testDB</ownerDesignName>
</ForeignKey>
<ForeignKey class="oracle.dbtools.crest.model.design.storage.oracle.v10g.FKProxyOraclev10g" name="CUST_ISA_PERSON" id="F7304E98-8098-110B-0A62-44E4F4841ED7">
<createdBy>morne</createdBy>
<createdTime>2019-05-10 06:39:00 UTC</createdTime>
<ownerDesignName>testDB</ownerDesignName>
</ForeignKey>
</foreignKeys>
<primaryKeys>
<PrimaryKey class="oracle.dbtools.crest.model.design.storage.oracle.v10g.PKProxyOraclev10g" name="CUSTOMER_PK" id="CBBD4DC5-5A13-9A3E-EC22-54A7DA5A635E">
<createdBy>morne</createdBy>
<createdTime>2019-05-10 06:39:00 UTC</createdTime>
<ownerDesignName>testDB</ownerDesignName>
<segment>9F6B1C94-F925-41C6-409C-5430207B896B</segment>
<tableSpace>577F16CB-4515-0AC8-9A34-547917F569D0</tableSpace>
<existingIndex>A1F5F6C1-4CE6-6F02-6B3D-D043EFBB0457</existingIndex>
<indexSegment>9F6B1C94-F925-41C6-409C-5430207B896B</indexSegment>
<indexSort>SORTED</indexSort>
<usingIndex>BY INDEX NAME</usingIndex>
</PrimaryKey>
</primaryKeys>
</TableProxyOraclev11g>